fittings/__init__.py
fittings/admin.py
fittings/app_settings.py
fittings/apps.py
fittings/auth_hooks.py
fittings/forms.py
fittings/models.py
fittings/providers.py
fittings/tasks.py
fittings/tests.py
fittings/urls.py
fittings/views.py
fittings/cogs/fittings.py
fittings/locale/de/LC_MESSAGES/django.mo
fittings/locale/de/LC_MESSAGES/django.po
fittings/locale/en/LC_MESSAGES/django.mo
fittings/locale/en/LC_MESSAGES/django.po
fittings/locale/es/LC_MESSAGES/django.mo
fittings/locale/es/LC_MESSAGES/django.po
fittings/locale/fr_FR/LC_MESSAGES/django.mo
fittings/locale/fr_FR/LC_MESSAGES/django.po
fittings/locale/ja/LC_MESSAGES/django.mo
fittings/locale/ja/LC_MESSAGES/django.po
fittings/locale/ko_KR/LC_MESSAGES/django.mo
fittings/locale/ko_KR/LC_MESSAGES/django.po
fittings/locale/ru/LC_MESSAGES/django.mo
fittings/locale/ru/LC_MESSAGES/django.po
fittings/locale/zh_Hans/LC_MESSAGES/django.mo
fittings/locale/zh_Hans/LC_MESSAGES/django.po
fittings/management/commands/fittings_preload_data.py
fittings/migrations/0001_initial.py
fittings/migrations/0002_add_dgm_unique_constraints.py
fittings/migrations/0003_remove_type_description_not_null.py
fittings/migrations/0004_add_item_category_and_group.py
fittings/migrations/0005_unicategory.py
fittings/migrations/0006_auto_20200605_0724.py
fittings/migrations/0007_auto_20200605_0735.py
fittings/migrations/0008_auto_20200605_0736.py
fittings/migrations/0009_auto_20200605_2117.py
fittings/migrations/0010_auto_20200718_2227.py
fittings/migrations/0011_auto_20200815_2022.py
fittings/migrations/0012_typehistory.py
fittings/migrations/0013_alter_doctrine_description.py
fittings/migrations/0014_serverversion.py
fittings/migrations/0015_fitting_created_fitting_last_updated_and_more.py
fittings/migrations/0016_remove_dogmaattribute_type_remove_dogmaeffect_type_and_more.py
fittings/migrations/__init__.py
fittings/static/fittings/ajax/libs/jquery.quicksearch/2.4.0/jquery.quicksearch.min.js
fittings-2.2.1.dist-info/METADATA
fittings-2.2.1.dist-info/WHEEL
fittings-2.2.1.dist-info/licenses/LICENSE
fittings-2.2.1.dist-info/RECORD
