Metadata-Version: 2.4
Name: fittings
Version: 2.2.1
Summary: A simple fittings and doctrine management application.
Project-URL: Documentation, https://gitlab.com/colcrunch/fittings/-/blob/master/README.md
Project-URL: Homepage, https://gitlab.com/colcrunch/fittings
Project-URL: Source, https://gitlab.com/colcrunch/fittings.git
Project-URL: Tracker, https://gitlab.com/colcrunch/fittings/-/issues
Author-email: Col Crunch <it-team@serin.space>
License:                     GNU GENERAL PUBLIC LICENSE
License-File: LICENSE
Keywords: allianceauth,doctrines,eveonline,fittings
Classifier: Environment :: Web Environment
Classifier: Framework :: Django
Classifier: Framework :: Django :: 3.2
Classifier: Framework :: Django :: 4.0
Classifier: Framework :: Django :: 4.1
Classifier: Intended Audience :: Developers
Classifier: License :: OSI Approved :: GNU General Public License v3 (GPLv3)
Classifier: Operating System :: POSIX :: Linux
Classifier: Programming Language :: Python
Classifier: Programming Language :: Python :: 3 :: Only
Classifier: Programming Language :: Python :: 3.10
Classifier: Programming Language :: Python :: 3.11
Classifier: Programming Language :: Python :: 3.12
Classifier: Programming Language :: Python :: 3.13
Classifier: Topic :: Internet :: WWW/HTTP
Classifier: Topic :: Internet :: WWW/HTTP :: Dynamic Content
Requires-Python: >=3.10
Requires-Dist: allianceauth>=4
Requires-Dist: django-eveuniverse>=1.6
Requires-Dist: django-model-utils>=3.1.1
Provides-Extra: discordbot
Requires-Dist: allianceauth-discordbot>=3.8; extra == 'discordbot'
